ipinfo/__init__.py
ipinfo/bogon.py
ipinfo/data.py
ipinfo/details.py
ipinfo/error.py
ipinfo/exceptions.py
ipinfo/handler.py
ipinfo/handler_async.py
ipinfo/handler_lite.py
ipinfo/handler_lite_async.py
ipinfo/handler_utils.py
ipinfo/version.py
ipinfo/cache/__init__.py
ipinfo/cache/default.py
ipinfo/cache/interface.py
ipinfo-5.2.1.dist-info/LICENSE
ipinfo-5.2.1.dist-info/METADATA
ipinfo-5.2.1.dist-info/WHEEL
ipinfo-5.2.1.dist-info/top_level.txt
ipinfo-5.2.1.dist-info/RECORD
