Metadata-Version: 2.1
Name: ipinfo
Version: 5.2.1
Summary: Official Python library for IPInfo
Home-page: https://github.com/ipinfo/python
Author: IPinfo
Author-email: support@ipinfo.io
License: Apache License 2.0
License-File: LICENSE
